floopcli/__init__.py
floopcli/__main__.py
floopcli/cli.py
floopcli/config.py
floopcli/log.yaml
floopcli/iot/__init__.py
floopcli/iot/core.py
floopcli/test/__init__.py
floopcli/test/fixture.py
floopcli/test/floop_test/__init__.py
floopcli/test/floop_test/cli_test.py
floopcli/test/floop_test/config_test.py
floopcli/test/iot_test/__init__.py
floopcli/test/iot_test/core_test.py
floopcli/test/util_test/__init__.py
floopcli/test/util_test/test_syscall.py
floopcli/util/__init__.py
floopcli/util/log.py
floopcli/util/syscall.py
floopcli-0.0.1a7.dist-info/DESCRIPTION.rst
floopcli-0.0.1a7.dist-info/LICENSE.txt
floopcli-0.0.1a7.dist-info/METADATA
floopcli-0.0.1a7.dist-info/RECORD
floopcli-0.0.1a7.dist-info/WHEEL
floopcli-0.0.1a7.dist-info/entry_points.txt
floopcli-0.0.1a7.dist-info/metadata.json
floopcli-0.0.1a7.dist-info/top_level.txt
