Metadata-Version: 2.0
Name: floopcli
Version: 0.0.1a7
Summary: sensor development and testing tools
Home-page: https://github.com/ForwardLoopLLC/floopcli
Author: Forward Loop LLC
Author-email: nick@forward-loop.com
License: UNKNOWN
Keywords: sensor development devops
Platform: UNKNOWN
Classifier: Development Status :: 3 - Alpha
Classifier: Intended Audience :: Developers
Classifier: Topic :: Software Development :: Build Tools
Classifier: License :: OSI Approved :: MIT License
Classifier: Programming Language :: Python :: 2
Classifier: Programming Language :: Python :: 3
Requires-Dist: pyyaml (>=3.12)
Requires-Dist: typing (>=3.6.4)
Provides-Extra: docs
Requires-Dist: sphinx (>=1.7.4); extra == 'docs'
Requires-Dist: sphinx-tabs (>=1.1.7); extra == 'docs'
Provides-Extra: test
Requires-Dist: pytest (>=3.5.1); extra == 'test'
Requires-Dist: pytest-cov (>=2.5.1); extra == 'test'
Provides-Extra: typing
Requires-Dist: mypy (>=0.0.590); extra == 'typing'
